roodkcab/__init__.py
roodkcab/backroundworker.py
roodkcab/data.py
roodkcab/filehelper.py
roodkcab/gitHelper.py
roodkcab-3.4.dist-info/LICENSE
roodkcab-3.4.dist-info/METADATA
roodkcab-3.4.dist-info/WHEEL
roodkcab-3.4.dist-info/top_level.txt
roodkcab-3.4.dist-info/RECORD
