Metadata-Version: 2.1
Name: roodkcab
Version: 3.4
Summary: Used Setx to set Variable Global!
Author-email: LuxxDEV <lkgames256@gmail.com>
Project-URL: Homepage, https://github.com/lkgames256/roodkcab
Project-URL: Bug Tracker, https://github.com/lkgames256/roodkcab/issues
Classifier: Programming Language :: Python :: 3
Classifier: License :: OSI Approved :: MIT License
Classifier: Operating System :: OS Independent
Requires-Python: >=3.9
License-File: LICENSE
Requires-Dist: rich
Requires-Dist: configparser
Requires-Dist: requests
Requires-Dist: gitpython
